[
  {
    "pinList": [],
    "location": "",
    "center": [40.73061, -73.935242],
    "zoom": 13,
    "orientation": "portrait",
    "textPrimary": "",
    "textSecondary": "",
    "textCoordinates": "N 40째43'50.2\" W 73째56'6.87\"",
    "styling": "basic",
    "size": "_24_36",
    "tileLayer": "dark-transit",
    "bbox": "{\"_southWest\":{\"lat\":40.67673250467168,\"lng\":-73.98262023925783},\"_northEast\":{\"lat\":40.78444086438884,\"lng\":-73.8878631591797}}",
    "tileZoomOffset": "2",
    "quantity": 1,
    "description": "Map near 3820 Review Ave, Long Island City, NY 11101, USA",
    "id": "a33aff8c-1298-4b1e-bf05-f9a3cf5b1714",
    "name": "Personalized Map",
    "unitPrice": 699,
    "lineItemId": [
      {
        "id": "item_7RyWOwmK5nEa2V",
        "product_id": "prod_VKXmwDy717orgD",
        "name": "Personalized Map",
        "product_name": "Personalized Map",
        "sku": null,
        "permalink": "qNG91W",
        "quantity": 1,
        "price": {
          "raw": 699,
          "formatted": "699.00",
          "formatted_with_symbol": "$699.00",
          "formatted_with_code": "699.00 USD"
        },
        "line_total": {
          "raw": 699,
          "formatted": "699.00",
          "formatted_with_symbol": "$699.00",
          "formatted_with_code": "699.00 USD"
        },
        "is_valid": true,
        "product_meta": [],
        "selected_options": [],
        "variant": null,
        "image": {
          "id": "ast_zkK6oL4p3VoXn0",
          "url": "https://cdn.chec.io/merchants/47490/assets/bRdYbK5ondeqWnwt|prod-pic-commerce.png",
          "description": null,
          "is_image": true,
          "filename": "prod-pic-commerce.png",
          "file_size": 676402,
          "file_extension": "png",
          "image_dimensions": { "width": 800, "height": 800 },
          "meta": [],
          "created_at": 1674768264,
          "updated_at": 1674768267
        },
        "tax": null
      }
    ],
    "isTransparentTextBlock": true,
    "styling_specs": {},
    "text_styling_specs": {
      "id": "dark-transit",
      "iconImg": "/blackWhiteSquareIcon.svg",
      "url": "https://api.maptiler.com/maps/265e1571-5b2a-47cf-bdf4-0f78abaefb47/{z}/{x}/{y}.png?key=fLxXsh3K0MP3y21i3bJs",
      "text": {
        "fontFamily": {
          "primary": "Semplicita",
          "secondary": "Semplicita",
          "coordinate": "Semplicita"
        },
        "size": { "primary": "24", "secondary": "12", "coordinate": "8" },
        "color": {
          "background": "#FFFFFF",
          "primary": "#000000",
          "secondary": "#000000",
          "coordinate": "#000000"
        },
        "color_transparent": {
          "background": "#0000",
          "primary": "#FFFFFF",
          "secondary": "#FFFFFF",
          "coordinate": "#FFFFFF"
        },
        "textBlock": { "padding": "8px", "rounded": "8px", "spacing": "1" }
      }
    },
    "mapDimensionsIn": {
      "map_width": 24,
      "map_height": 36,
      "map_pixel_multiplier": 23
    }
  },
  {
    "pinList": [],
    "location": "",
    "center": [40.73061, -73.935242],
    "zoom": 13,
    "orientation": "portrait",
    "textPrimary": "",
    "textSecondary": "",
    "textCoordinates": "N 40째43'50.2\" W 73째56'6.87\"",
    "styling": "basic",
    "size": "_24_36",
    "tileLayer": "dark-transit",
    "bbox": "{\"_southWest\":{\"lat\":40.67673250467168,\"lng\":-73.98262023925783},\"_northEast\":{\"lat\":40.78444086438884,\"lng\":-73.8878631591797}}",
    "tileZoomOffset": "2",
    "quantity": 1,
    "description": "Map near 3820 Review Ave, Long Island City, NY 11101, USA",
    "id": "54299567-47df-488f-9b6f-40b3d8fcedcf",
    "name": "Personalized Map",
    "unitPrice": 699,
    "lineItemId": [
      {
        "id": "item_7RyWOwmK5nEa2V",
        "product_id": "prod_VKXmwDy717orgD",
        "name": "Personalized Map",
        "product_name": "Personalized Map",
        "sku": null,
        "permalink": "qNG91W",
        "quantity": 2,
        "price": {
          "raw": 699,
          "formatted": "699.00",
          "formatted_with_symbol": "$699.00",
          "formatted_with_code": "699.00 USD"
        },
        "line_total": {
          "raw": 1398,
          "formatted": "1,398.00",
          "formatted_with_symbol": "$1,398.00",
          "formatted_with_code": "1,398.00 USD"
        },
        "is_valid": true,
        "product_meta": [],
        "selected_options": [],
        "variant": null,
        "image": {
          "id": "ast_zkK6oL4p3VoXn0",
          "url": "https://cdn.chec.io/merchants/47490/assets/bRdYbK5ondeqWnwt|prod-pic-commerce.png",
          "description": null,
          "is_image": true,
          "filename": "prod-pic-commerce.png",
          "file_size": 676402,
          "file_extension": "png",
          "image_dimensions": { "width": 800, "height": 800 },
          "meta": [],
          "created_at": 1674768264,
          "updated_at": 1674768267
        },
        "tax": null
      }
    ],
    "isTransparentTextBlock": true,
    "styling_specs": {},
    "text_styling_specs": {
      "id": "dark-transit",
      "iconImg": "/blackWhiteSquareIcon.svg",
      "url": "https://api.maptiler.com/maps/265e1571-5b2a-47cf-bdf4-0f78abaefb47/{z}/{x}/{y}.png?key=fLxXsh3K0MP3y21i3bJs",
      "text": {
        "fontFamily": {
          "primary": "Semplicita",
          "secondary": "Semplicita",
          "coordinate": "Semplicita"
        },
        "size": { "primary": "24", "secondary": "12", "coordinate": "8" },
        "color": {
          "background": "#FFFFFF",
          "primary": "#000000",
          "secondary": "#000000",
          "coordinate": "#000000"
        },
        "color_transparent": {
          "background": "#0000",
          "primary": "#FFFFFF",
          "secondary": "#FFFFFF",
          "coordinate": "#FFFFFF"
        },
        "textBlock": { "padding": "8px", "rounded": "8px", "spacing": "1" }
      }
    },
    "mapDimensionsIn": {
      "map_width": 24,
      "map_height": 36,
      "map_pixel_multiplier": 23
    }
  },
  {
    "pinList": [],
    "location": "",
    "center": [40.73061, -73.935242],
    "zoom": 13,
    "orientation": "landscape",
    "textPrimary": "",
    "textSecondary": "",
    "textCoordinates": "",
    "styling": "basic",
    "size": "_24_36",
    "tileLayer": "dark-transit",
    "bbox": "{\"_southWest\":{\"lat\":40.69469600456701,\"lng\":-74.00630950927736},\"_northEast\":{\"lat\":40.76650157923057,\"lng\":-73.86417388916017}}",
    "tileZoomOffset": "2",
    "quantity": 1,
    "description": "Map near 3820 Review Ave, Long Island City, NY 11101, USA",
    "id": "5fd2fb26-de42-4549-846d-3e00d9b58302",
    "name": "Personalized Map",
    "unitPrice": 699,
    "lineItemId": [
      {
        "id": "item_7RyWOwmK5nEa2V",
        "product_id": "prod_VKXmwDy717orgD",
        "name": "Personalized Map",
        "product_name": "Personalized Map",
        "sku": null,
        "permalink": "qNG91W",
        "quantity": 3,
        "price": {
          "raw": 699,
          "formatted": "699.00",
          "formatted_with_symbol": "$699.00",
          "formatted_with_code": "699.00 USD"
        },
        "line_total": {
          "raw": 2097,
          "formatted": "2,097.00",
          "formatted_with_symbol": "$2,097.00",
          "formatted_with_code": "2,097.00 USD"
        },
        "is_valid": true,
        "product_meta": [],
        "selected_options": [],
        "variant": null,
        "image": {
          "id": "ast_zkK6oL4p3VoXn0",
          "url": "https://cdn.chec.io/merchants/47490/assets/bRdYbK5ondeqWnwt|prod-pic-commerce.png",
          "description": null,
          "is_image": true,
          "filename": "prod-pic-commerce.png",
          "file_size": 676402,
          "file_extension": "png",
          "image_dimensions": { "width": 800, "height": 800 },
          "meta": [],
          "created_at": 1674768264,
          "updated_at": 1674768267
        },
        "tax": null
      }
    ],
    "isTransparentTextBlock": false,
    "styling_specs": {},
    "text_styling_specs": {
      "id": "dark-transit",
      "iconImg": "/blackWhiteSquareIcon.svg",
      "url": "https://api.maptiler.com/maps/265e1571-5b2a-47cf-bdf4-0f78abaefb47/{z}/{x}/{y}.png?key=fLxXsh3K0MP3y21i3bJs",
      "text": {
        "fontFamily": {
          "primary": "Semplicita",
          "secondary": "Semplicita",
          "coordinate": "Semplicita"
        },
        "size": { "primary": "24", "secondary": "12", "coordinate": "8" },
        "color": {
          "background": "#FFFFFF",
          "primary": "#000000",
          "secondary": "#000000",
          "coordinate": "#000000"
        },
        "color_transparent": {
          "background": "#0000",
          "primary": "#FFFFFF",
          "secondary": "#FFFFFF",
          "coordinate": "#FFFFFF"
        },
        "textBlock": { "padding": "8px", "rounded": "8px", "spacing": "1" }
      }
    },
    "mapDimensionsIn": {
      "map_width": 35,
      "map_height": 23,
      "map_pixel_multiplier": 23
    }
  },
  {
    "pinList": [],
    "location": "",
    "center": [40.73061, -73.935242],
    "zoom": 13,
    "orientation": "landscape",
    "textPrimary": "",
    "textSecondary": "",
    "textCoordinates": "",
    "styling": "basic",
    "size": "_24_36",
    "tileLayer": "dark-transit",
    "bbox": "{\"_southWest\":{\"lat\":40.69469600456701,\"lng\":-74.00630950927736},\"_northEast\":{\"lat\":40.76650157923057,\"lng\":-73.86417388916017}}",
    "tileZoomOffset": "2",
    "quantity": 1,
    "description": "Map near 3820 Review Ave, Long Island City, NY 11101, USA",
    "id": "60e60ad9-887a-4f4f-a9fc-4ca0b6be9abc",
    "name": "Personalized Map",
    "unitPrice": 699,
    "lineItemId": [
      {
        "id": "item_7RyWOwmK5nEa2V",
        "product_id": "prod_VKXmwDy717orgD",
        "name": "Personalized Map",
        "product_name": "Personalized Map",
        "sku": null,
        "permalink": "qNG91W",
        "quantity": 4,
        "price": {
          "raw": 699,
          "formatted": "699.00",
          "formatted_with_symbol": "$699.00",
          "formatted_with_code": "699.00 USD"
        },
        "line_total": {
          "raw": 2796,
          "formatted": "2,796.00",
          "formatted_with_symbol": "$2,796.00",
          "formatted_with_code": "2,796.00 USD"
        },
        "is_valid": true,
        "product_meta": [],
        "selected_options": [],
        "variant": null,
        "image": {
          "id": "ast_zkK6oL4p3VoXn0",
          "url": "https://cdn.chec.io/merchants/47490/assets/bRdYbK5ondeqWnwt|prod-pic-commerce.png",
          "description": null,
          "is_image": true,
          "filename": "prod-pic-commerce.png",
          "file_size": 676402,
          "file_extension": "png",
          "image_dimensions": { "width": 800, "height": 800 },
          "meta": [],
          "created_at": 1674768264,
          "updated_at": 1674768267
        },
        "tax": null
      }
    ],
    "isTransparentTextBlock": false,
    "styling_specs": {},
    "text_styling_specs": {
      "id": "dark-transit",
      "iconImg": "/blackWhiteSquareIcon.svg",
      "url": "https://api.maptiler.com/maps/265e1571-5b2a-47cf-bdf4-0f78abaefb47/{z}/{x}/{y}.png?key=fLxXsh3K0MP3y21i3bJs",
      "text": {
        "fontFamily": {
          "primary": "Semplicita",
          "secondary": "Semplicita",
          "coordinate": "Semplicita"
        },
        "size": { "primary": "24", "secondary": "12", "coordinate": "8" },
        "color": {
          "background": "#FFFFFF",
          "primary": "#000000",
          "secondary": "#000000",
          "coordinate": "#000000"
        },
        "color_transparent": {
          "background": "#0000",
          "primary": "#FFFFFF",
          "secondary": "#FFFFFF",
          "coordinate": "#FFFFFF"
        },
        "textBlock": { "padding": "8px", "rounded": "8px", "spacing": "1" }
      }
    },
    "mapDimensionsIn": {
      "map_width": 35,
      "map_height": 23,
      "map_pixel_multiplier": 23
    }
  },
  {
    "pinList": [],
    "location": "",
    "center": [40.73061, -73.935242],
    "zoom": 13,
    "orientation": "portrait",
    "textPrimary": "",
    "textSecondary": "",
    "textCoordinates": "",
    "styling": "basic",
    "size": "_24_36",
    "tileLayer": "city-lights",
    "bbox": "{\"_southWest\":{\"lat\":40.67673250467168,\"lng\":-73.98262023925783},\"_northEast\":{\"lat\":40.78444086438884,\"lng\":-73.8878631591797}}",
    "tileZoomOffset": "2",
    "quantity": 1,
    "description": "Map near 3820 Review Ave, Long Island City, NY 11101, USA",
    "id": "38d8642e-8fb0-4904-8476-54ba1574848b",
    "name": "Personalized Map",
    "unitPrice": 699,
    "lineItemId": [
      {
        "id": "item_7RyWOwmK5nEa2V",
        "product_id": "prod_VKXmwDy717orgD",
        "name": "Personalized Map",
        "product_name": "Personalized Map",
        "sku": null,
        "permalink": "qNG91W",
        "quantity": 5,
        "price": {
          "raw": 699,
          "formatted": "699.00",
          "formatted_with_symbol": "$699.00",
          "formatted_with_code": "699.00 USD"
        },
        "line_total": {
          "raw": 3495,
          "formatted": "3,495.00",
          "formatted_with_symbol": "$3,495.00",
          "formatted_with_code": "3,495.00 USD"
        },
        "is_valid": true,
        "product_meta": [],
        "selected_options": [],
        "variant": null,
        "image": {
          "id": "ast_zkK6oL4p3VoXn0",
          "url": "https://cdn.chec.io/merchants/47490/assets/bRdYbK5ondeqWnwt|prod-pic-commerce.png",
          "description": null,
          "is_image": true,
          "filename": "prod-pic-commerce.png",
          "file_size": 676402,
          "file_extension": "png",
          "image_dimensions": { "width": 800, "height": 800 },
          "meta": [],
          "created_at": 1674768264,
          "updated_at": 1674768267
        },
        "tax": null
      }
    ],
    "isTransparentTextBlock": false,
    "styling_specs": {},
    "text_styling_specs": {
      "id": "city-lights",
      "iconImg": "/city-lights.png",
      "url": "https://api.maptiler.com/maps/70207988-ec48-4dce-8172-230ff9375b7d/{z}/{x}/{y}.png?key=fLxXsh3K0MP3y21i3bJs",
      "text": {
        "fontFamily": {
          "primary": "Semplicita",
          "secondary": "Semplicita",
          "coordinate": "Semplicita"
        },
        "size": { "primary": "24", "secondary": "12", "coordinate": "8" },
        "color": {
          "background": "#000000",
          "primary": "#ffd900",
          "secondary": "#ffd900",
          "coordinate": "#ffd900"
        },
        "color_transparent": {
          "background": "#0000",
          "primary": "#ffd900",
          "secondary": "#ffd900",
          "coordinate": "#ffd900"
        },
        "textBlock": { "padding": "8px", "rounded": "8px", "spacing": "1" }
      }
    },
    "mapDimensionsIn": {
      "map_width": 23,
      "map_height": 35,
      "map_pixel_multiplier": 23
    }
  },
  {
    "pinList": [],
    "location": "",
    "center": [40.73061, -73.935242],
    "zoom": 13,
    "orientation": "landscape",
    "textPrimary": "",
    "textSecondary": "",
    "textCoordinates": "",
    "styling": "basic",
    "size": "_24_36",
    "tileLayer": "city-lights",
    "bbox": "{\"_southWest\":{\"lat\":40.69469600456701,\"lng\":-74.00630950927736},\"_northEast\":{\"lat\":40.76650157923057,\"lng\":-73.86417388916017}}",
    "tileZoomOffset": "2",
    "quantity": 1,
    "description": "Map near 3820 Review Ave, Long Island City, NY 11101, USA",
    "id": "258b773e-5f28-4e1e-a7e1-0818e3d81b56",
    "name": "Personalized Map",
    "unitPrice": 699,
    "lineItemId": [
      {
        "id": "item_7RyWOwmK5nEa2V",
        "product_id": "prod_VKXmwDy717orgD",
        "name": "Personalized Map",
        "product_name": "Personalized Map",
        "sku": null,
        "permalink": "qNG91W",
        "quantity": 6,
        "price": {
          "raw": 699,
          "formatted": "699.00",
          "formatted_with_symbol": "$699.00",
          "formatted_with_code": "699.00 USD"
        },
        "line_total": {
          "raw": 4194,
          "formatted": "4,194.00",
          "formatted_with_symbol": "$4,194.00",
          "formatted_with_code": "4,194.00 USD"
        },
        "is_valid": true,
        "product_meta": [],
        "selected_options": [],
        "variant": null,
        "image": {
          "id": "ast_zkK6oL4p3VoXn0",
          "url": "https://cdn.chec.io/merchants/47490/assets/bRdYbK5ondeqWnwt|prod-pic-commerce.png",
          "description": null,
          "is_image": true,
          "filename": "prod-pic-commerce.png",
          "file_size": 676402,
          "file_extension": "png",
          "image_dimensions": { "width": 800, "height": 800 },
          "meta": [],
          "created_at": 1674768264,
          "updated_at": 1674768267
        },
        "tax": null
      }
    ],
    "isTransparentTextBlock": false,
    "styling_specs": {},
    "text_styling_specs": {
      "id": "city-lights",
      "iconImg": "/city-lights.png",
      "url": "https://api.maptiler.com/maps/70207988-ec48-4dce-8172-230ff9375b7d/{z}/{x}/{y}.png?key=fLxXsh3K0MP3y21i3bJs",
      "text": {
        "fontFamily": {
          "primary": "Semplicita",
          "secondary": "Semplicita",
          "coordinate": "Semplicita"
        },
        "size": { "primary": "24", "secondary": "12", "coordinate": "8" },
        "color": {
          "background": "#000000",
          "primary": "#ffd900",
          "secondary": "#ffd900",
          "coordinate": "#ffd900"
        },
        "color_transparent": {
          "background": "#0000",
          "primary": "#ffd900",
          "secondary": "#ffd900",
          "coordinate": "#ffd900"
        },
        "textBlock": { "padding": "8px", "rounded": "8px", "spacing": "1" }
      }
    },
    "mapDimensionsIn": {
      "map_width": 35,
      "map_height": 23,
      "map_pixel_multiplier": 23
    }
  }
]
